mindspore/.commit_id
mindspore/__init__.py
mindspore/_ascend_mpi.cpython-39-aarch64-linux-gnu.so
mindspore/_c_dataengine.cpython-39-aarch64-linux-gnu.so
mindspore/_c_expression.cpython-39-aarch64-linux-gnu.so
mindspore/_c_mindrecord.cpython-39-aarch64-linux-gnu.so
mindspore/_checkparam.py
mindspore/_mindspore_offline_debug.cpython-39-aarch64-linux-gnu.so
mindspore/context.py
mindspore/default_config.py
mindspore/log.py
mindspore/version.py
mindspore/_akg/__init__.py
mindspore/_akg/akg/__init__.py
mindspore/_akg/akg/autodiff.py
mindspore/_akg/akg/build_module.py
mindspore/_akg/akg/dim.py
mindspore/_akg/akg/global_configs.py
mindspore/_akg/akg/backend/__init__.py
mindspore/_akg/akg/backend/aic_model.py
mindspore/_akg/akg/backend/parsing_profiling_data.py
mindspore/_akg/akg/composite/__init__.py
mindspore/_akg/akg/composite/build_module.py
mindspore/_akg/akg/composite/peel.py
mindspore/_akg/akg/composite/split_block.py
mindspore/_akg/akg/composite/split_stitch.py
mindspore/_akg/akg/composite/topi.py
mindspore/_akg/akg/config/repository.json
mindspore/_akg/akg/config/repository_gpu.json
mindspore/_akg/akg/contrib/__init__.py
mindspore/_akg/akg/include/akg_mma_lib/wmma.hpp
mindspore/_akg/akg/include/akg_random/random.cuh
mindspore/_akg/akg/include/akg_reduce/README.md
mindspore/_akg/akg/include/akg_reduce/reduce.cuh
mindspore/_akg/akg/include/akg_reduce/algorithm/reduce_impl.cuh
mindspore/_akg/akg/include/akg_reduce/algorithm/shared_reduce.cuh
mindspore/_akg/akg/include/akg_reduce/operators/reduce_operators.cuh
mindspore/_akg/akg/include/akg_reduce/utils/util.cuh
mindspore/_akg/akg/include/paris_reduce/paris_reduce.cuh
mindspore/_akg/akg/lang/__init__.py
mindspore/_akg/akg/lang/cce/__init__.py
mindspore/_akg/akg/lang/cce/te_compute/__init__.py
mindspore/_akg/akg/lang/cce/te_compute/broadcast_compute.py
mindspore/_akg/akg/lang/cce/te_compute/cast_compute.py
mindspore/_akg/akg/lang/cce/te_compute/common.py
mindspore/_akg/akg/lang/cce/te_compute/concat_compute.py
mindspore_ascend-1.5.2.dist-info/METADATA
mindspore_ascend-1.5.2.dist-info/WHEEL
mindspore_ascend-1.5.2.dist-info/entry_points.txt
mindspore_ascend-1.5.2.dist-info/top_level.txt
mindspore_ascend-1.5.2.dist-info/RECORD
